<OSS xmlns="http://www.vinodh.com/OSSXML" 
xmlns:xsi="http://www.w3.org/2001/XMLSchema-instance" 
xsi:schemaLocation="http://www.vinodh.com/OSSXML ossxml.xsd">
    <Request>
        <RequestType>add</RequestType>
        <RequestMode>offline</RequestMode>
        <SessionID>1234512345</SessionID>
        <operName>vinodh</operName>
        <Version>2.4</Version>
    </Request>
    <RequestElement>
        <Attribute>
            <Name>Parent_Type</Name>
            <Value>Device</Value>
        </Attribute>
        <Attribute>
            <Name>Parent_Id</Name>
            <Value>1000234</Value>
        </Attribute>
        <Attribute>
            <Name>Handle_Type</Name>
            <Value>DynOmciCpeConnection</Value>
        </Attribute>
        <Attribute>
            <Name>Handle_Id</Name>
            <Value>1000224</Value>
        </Attribute>
        <Attribute>
            <Name>Filter_Condition</Name>
            <Value>shelfId=3</Value>
        </Attribute>
        <Attribute>
            <Name>Filter_Condition</Name>
            <Value>cardId=1</Value>
        </Attribute>
        <Attribute>
            <Name>phyShelfId</Name>
            <Value>3</Value>
        </Attribute>
        <Attribute>
            <Name>gponOltId</Name>
            <Value>5</Value>
        </Attribute>
        <Attribute>
            <Name>phySlotId</Name>
            <Value>1</Value>
        </Attribute>
    </RequestElement>
</OSS>